{
	"items": [
		{
			"id": "1",
			"tags": ["Trees"],
			"price": 10.99,
			"name": "Handcrafted Trees Mug",
			"description": "enim corporis voluptatibus laudantium possimus alias dolorem voluptatem similique aut aliquam voluptatem voluptatem omnis id consequatur",
			"slug": "Handcrafted-Trees-Mug",
			"added": 1485723766805,
			"manufacturer": "OHara-Group",
			"itemType": "mug"
		},
		{
			"id": "2",
			"tags": ["Beach", "Ocean", "Water"],
			"price": 19.99,
			"name": "Rustic Beach Mug",
			"description": "totam at veritatis eligendi assumenda ex quia praesentium quibusdam ducimus",
			"slug": "Rustic-Beach-Mug",
			"added": 1481573896833,
			"manufacturer": "Sipes-Inc",
			"itemType": "mug"
		},
		{
			"id": "3",
			"tags": ["Animal", "Bear"],
			"price": 17.99,
			"name": "Handcrafted Bear Mug",
			"description": "vitae mollitia et in accusantium est voluptas officiis est non",
			"slug": "Handcrafted-Bear-Mug",
			"added": 1485991071829,
			"manufacturer": "Weissnat-Schowalter-and-Koelpin",
			"itemType": "mug"
		},
		{
			"id": "4",
			"tags": ["Road"],
			"price": 15.99,
			"name": "Refined Road Mug",
			"description": "explicabo fugit magnam fugit dolorem itaque unde quidem est quia ut a veritatis sit facere possimus fugit ipsam",
			"slug": "Refined-Road-Mug",
			"added": 1482213983048,
			"manufacturer": "Bernier-Hane",
			"itemType": "mug"
		},
		{
			"id": "5",
			"tags": ["Ocean", "Rocks"],
			"price": 10.99,
			"name": "Unbranded Ocean Mug",
			"description": "facilis aut velit vitae sit dolorum illum nostrum pariatur dolorem vel atque quasi placeat qui",
			"slug": "Unbranded-Ocean-Mug",
			"added": 1483408192004,
			"manufacturer": "Franecki---Gaylord",
			"itemType": "mug"
		},
		{
			"id": "6",
			"tags": ["Sunset", "Beach", "Ocean"],
			"price": 9.99,
			"name": "Rustic Ocean Mug",
			"description": "libero reprehenderit blanditiis quidem laborum ullam quae fuga consequuntur minima praesentium consequatur qui excepturi nostrum tempora sunt deleniti",
			"slug": "Rustic-Ocean-Mug",
			"added": 1485511118573,
			"manufacturer": "Bayer-and-Sons",
			"itemType": "mug"
		},
		{
			"id": "7",
			"tags": ["Rust", "Old", "Car"],
			"price": 19.99,
			"name": "Sleek Old Mug",
			"description": "necessitatibus suscipit iure quia voluptates voluptas quidem ipsum laboriosam adipisci",
			"slug": "Sleek-Old-Mug",
			"added": 1485759837725,
			"manufacturer": "Boyle-LLC",
			"itemType": "mug"
		},
		{
			"id": "8",
			"tags": ["Coffee"],
			"price": 14.99,
			"name": "Sleek Coffee Mug",
			"description": "et adipisci explicabo consequatur rerum voluptas dolorem qui omnis vel",
			"slug": "Sleek-Coffee-Mug",
			"added": 1479259996312,
			"manufacturer": "Franecki---Gaylord",
			"itemType": "mug"
		},
		{
			"id": "9",
			"tags": ["Trees", "Fog", "People"],
			"price": 16.99,
			"name": "Rustic Trees Mug",
			"description": "ut architecto est similique sit nostrum sit sed ipsa itaque aliquam nesciunt reprehenderit et neque aut id nulla dolore sed sit facere eligendi",
			"slug": "Rustic-Trees-Mug",
			"added": 1480664800826,
			"manufacturer": "Weissnat-Schowalter-and-Koelpin",
			"itemType": "mug"
		},
		{
			"id": "10",
			"tags": ["Person", "Night", "Stars"],
			"price": 17.99,
			"name": "Gorgeous Night Shirt",
			"description": "qui ex nobis est neque occaecati sunt quae quia voluptatem id ut atque rem nihil mollitia",
			"slug": "Gorgeous-Night-Shirt-1",
			"added": 1483744028073,
			"manufacturer": "Feil-Dooley-and-Reinger",
			"itemType": "shirt"
		},
		{
			"id": "11",
			"tags": ["Person", "Coffee", "Book", "Camera"],
			"price": 14.99,
			"name": "Small Person Shirt",
			"description": "adipisci enim consequuntur impedit culpa eos nesciunt possimus pariatur nam ab ipsa asperiores voluptas placeat et minima sunt aut laudantium amet est",
			"slug": "Small-Person-Shirt",
			"added": 1485172456727,
			"manufacturer": "McCullough---Lueilwitz",
			"itemType": "shirt"
		},
		{
			"id": "12",
			"tags": ["Flower"],
			"price": 15.99,
			"name": "Incredible Flower Shirt",
			"description": "explicabo autem et aliquid autem vitae corrupti officia dolore consequatur et magnam officia minima ut",
			"slug": "Incredible-Flower-Shirt",
			"added": 1484735897612,
			"manufacturer": "Cruickshank-Bayer-and-Gerlach",
			"itemType": "shirt"
		},
		{
			"id": "13",
			"tags": ["Mountain", "Trees", "Fog"],
			"price": 13.99,
			"name": "Ergonomic Mountain Shirt",
			"description": "placeat amet voluptas harum in minima vero nihil labore vero vel saepe quia",
			"slug": "Ergonomic-Mountain-Shirt-1",
			"added": 1481851489801,
			"manufacturer": "Leannon-Fahey-and-Sawayn",
			"itemType": "shirt"
		},
		{
			"id": "14",
			"tags": ["Desk", "Office", "Wood"],
			"price": 17.99,
			"name": "Handcrafted Wood Shirt",
			"description": "voluptatem dolores pariatur voluptates tenetur molestiae vitae totam est nisi dolor provident rem rerum totam",
			"slug": "Handcrafted-Wood-Shirt",
			"added": 1482000810699,
			"manufacturer": "Nikolaus-Schinner",
			"itemType": "shirt"
		},
		{
			"id": "15",
			"tags": ["Macro", "Bamboo"],
			"price": 15.99,
			"name": "Small Bamboo Shirt",
			"description": "temporibus quae autem voluptas iusto sint qui ullam nostrum tenetur",
			"slug": "Small-Bamboo-Shirt",
			"added": 1478282193128,
			"manufacturer": "Konopelski-Inc",
			"itemType": "shirt"
		},
		{
			"id": "16",
			"tags": ["Dog", "Animal", "Puppy"],
			"price": 18.99,
			"name": "Sleek Puppy Shirt",
			"description": "soluta quae voluptate cumque maiores corrupti repellat fugit quisquam a aliquid accusantium rem harum sint ex provident impedit ut et provident et quam",
			"slug": "Sleek-Puppy-Shirt",
			"added": 1486280696656,
			"manufacturer": "OHara-Group",
			"itemType": "shirt"
		},
		{
			"id": "17",
			"tags": ["City", "Buildings"],
			"price": 17.99,
			"name": "Awesome Buildings Shirt",
			"description": "autem reiciendis quae non asperiores aut quis labore exercitationem voluptatem et rerum quis tenetur",
			"slug": "Awesome-Buildings-Shirt-2",
			"added": 1478690559826,
			"manufacturer": "Leuschke-Smith-and-Conroy",
			"itemType": "shirt"
		},
		{
			"id": "18",
			"tags": ["Tree", "Fog"],
			"price": 10.99,
			"name": "Handcrafted Fog Shirt",
			"description": "nemo et quaerat possimus vel ad repellendus quia ex ex repellendus quia officia adipisci",
			"slug": "Handcrafted-Fog-Shirt-3",
			"added": 1477962579126,
			"manufacturer": "Metz---Kautzer",
			"itemType": "shirt"
		},
		{
			"id": "19",
			"tags": ["Sky", "Night"],
			"price": 10.99,
			"name": "Small Night Shirt",
			"description": "cum at rem nobis ad in adipisci ex dolore quam quia quis consectetur eius quibusdam ut sunt quibusdam corrupti est",
			"slug": "Small-Night-Shirt-3",
			"added": 1478677131565,
			"manufacturer": "Dickens-Franecki",
			"itemType": "shirt"
		},
		{
			"id": "20",
			"tags": ["Snow", "Mountains"],
			"price": 13.99,
			"name": "Rustic Mountains Shirt",
			"description": "est voluptas hic dolores ipsum vitae rerum molestiae repudiandae hic tempore",
			"slug": "Rustic-Mountains-Shirt-1",
			"added": 1481172184605,
			"manufacturer": "Rice-Inc",
			"itemType": "shirt"
		},
		{
			"id": "21",
			"tags": ["Ocean", "Water"],
			"price": 13.99,
			"name": "Unbranded Water Shirt",
			"description": "quas mollitia similique alias aut aut modi sequi accusantium eius inventore aliquid nisi inventore facilis placeat non officiis provident molestiae exercitationem voluptate rerum",
			"slug": "Unbranded-Water-Shirt-2",
			"added": 1484677371851,
			"manufacturer": "Bernier-Hane",
			"itemType": "shirt"
		},
		{
			"id": "22",
			"tags": ["Trees", "Nature", "Fog"],
			"price": 18.99,
			"name": "Generic Nature Shirt",
			"description": "a veniam aliquam non hic distinctio qui doloremque aut velit iure sapiente rerum ex et libero unde natus consequatur perspiciatis quis",
			"slug": "Generic-Nature-Shirt-2",
			"added": 1478763941271,
			"manufacturer": "Oberbrunner-Block-and-Mills",
			"itemType": "shirt"
		},
		{
			"id": "23",
			"tags": ["Plants", "Succulents"],
			"price": 20.99,
			"name": "Awesome Succulents Shirt",
			"description": "deleniti dolore consequuntur repudiandae qui omnis consectetur ut est vel voluptatibus",
			"slug": "Awesome-Succulents-Shirt",
			"added": 1486253491269,
			"manufacturer": "Leuschke-Smith-and-Conroy",
			"itemType": "shirt"
		},
		{
			"id": "24",
			"tags": ["Wave", "Ocean", "Water"],
			"price": 20.99,
			"name": "Intelligent Water Shirt",
			"description": "totam aut aliquam illo quas atque laborum enim quis laborum ducimus impedit dignissimos nostrum ex voluptatem id qui quaerat et",
			"slug": "Intelligent-Water-Shirt-1",
			"added": 1479930371917,
			"manufacturer": "Dickens-Franecki",
			"itemType": "shirt"
		},
		{
			"id": "25",
			"tags": ["Sunset", "Person", "Mountains", "Silhouette"],
			"price": 13.99,
			"name": "Handcrafted Silhouette Shirt",
			"description": "sit sapiente consequatur vel nesciunt sed et blanditiis voluptate deserunt et in sunt debitis odit voluptates dolores",
			"slug": "Handcrafted-Silhouette-Shirt",
			"added": 1481824051232,
			"manufacturer": "Bayer-and-Sons",
			"itemType": "shirt"
		},
		{
			"id": "26",
			"tags": ["Hand", "Night"],
			"price": 17.99,
			"name": "Incredible Night Shirt",
			"description": "aperiam cum minus eius placeat occaecati tenetur impedit id et dolore consequuntur ut iusto eaque voluptas atque eveniet fuga eligendi totam facilis sit sit",
			"slug": "Incredible-Night-Shirt",
			"added": 1486132957436,
			"manufacturer": "Bernier-Hane",
			"itemType": "shirt"
		},
		{
			"id": "27",
			"tags": ["Terminal", "Stairs"],
			"price": 19.99,
			"name": "Sleek Stairs Shirt",
			"description": "sed dolore et fuga alias esse ut non vitae doloremque ducimus",
			"slug": "Sleek-Stairs-Shirt",
			"added": 1480760751768,
			"manufacturer": "Feil-Dooley-and-Reinger",
			"itemType": "shirt"
		},
		{
			"id": "28",
			"tags": ["Fog", "Water"],
			"price": 15.99,
			"name": "Unbranded Water Shirt",
			"description": "aperiam temporibus modi mollitia et enim accusamus laboriosam molestiae ducimus ipsa ab fugit qui reiciendis ducimus quia et at consequatur est",
			"slug": "Unbranded-Water-Shirt-3",
			"added": 1478693503710,
			"manufacturer": "Weissnat-Schowalter-and-Koelpin",
			"itemType": "shirt"
		},
		{
			"id": "29",
			"tags": ["Sunset", "Snow", "Mountains"],
			"price": 19.99,
			"name": "Refined Sunset Shirt",
			"description": "commodi mollitia enim aspernatur sed ullam voluptas consequatur dolorem est dicta sit voluptatum et consequatur qui sequi nulla autem facere minus distinctio explicabo consectetur tempora",
			"slug": "Refined-Sunset-Shirt",
			"added": 1479003479547,
			"manufacturer": "Franecki---Gaylord",
			"itemType": "shirt"
		},
		{
			"id": "30",
			"tags": ["Snow", "Mountains"],
			"price": 20.99,
			"name": "Unbranded Mountains Shirt",
			"description": "nulla fugiat molestiae ratione tempore sed occaecati consequatur ut eum et autem",
			"slug": "Unbranded-Mountains-Shirt-2",
			"added": 1483781522680,
			"manufacturer": "Leuschke-Smith-and-Conroy",
			"itemType": "shirt"
		},
		{
			"id": "31",
			"tags": ["Arial", "Forest"],
			"price": 13.99,
			"name": "Rustic Arial Shirt",
			"description": "facilis harum facere rem quisquam enim quidem est provident deleniti non beatae repellat ullam qui enim et molestias laudantium deleniti aliquid",
			"slug": "Rustic-Arial-Shirt",
			"added": 1484527576669,
			"manufacturer": "Dickens-Franecki",
			"itemType": "shirt"
		},
		{
			"id": "32",
			"tags": ["Sunset", "Dock", "Ocean"],
			"price": 13.99,
			"name": "Handmade Ocean Shirt",
			"description": "quaerat omnis ab ab veritatis et ab enim amet voluptate quia aperiam eveniet beatae voluptas quidem consequatur nihil veniam maxime",
			"slug": "Handmade-Ocean-Shirt-2",
			"added": 1477819216248,
			"manufacturer": "Dickens-Franecki",
			"itemType": "shirt"
		}
	]
}
